pyaliyun/__init__.py
pyaliyun/aliyun.py
pyaliyun/base.py
pyaliyun/ecs.py
pyaliyun/rds.py
pyaliyun/slb.py
pyaliyunsdk-0.0.12.dist-info/METADATA
pyaliyunsdk-0.0.12.dist-info/WHEEL
pyaliyunsdk-0.0.12.dist-info/top_level.txt
pyaliyunsdk-0.0.12.dist-info/RECORD
