Metadata-Version: 2.1
Name: pyaliyunsdk
Version: 0.0.12
Summary: Aliyun SDK package
Home-page: https://github.com/Maliaotw/pyaliyun.git
Author: Maliao
Author-email: maliaotw@gmail.com
License: UNKNOWN
Platform: UNKNOWN
Classifier: Programming Language :: Python :: 3
Classifier: License :: OSI Approved :: MIT License
Classifier: Operating System :: OS Independent
Requires-Python: >=3.6
Requires-Dist: aliyun-python-sdk-core (==2.13.26)
Requires-Dist: aliyun-python-sdk-ecs (==4.19.12)
Requires-Dist: aliyun-python-sdk-rds (==2.5.1)
Requires-Dist: aliyun-python-sdk-slb (==3.2.18)
